pybw/__init__.py
pybw/core/__init__.py
pybw/core/trick/__init__.py
pybw/core/trick/lazy_import.py
pybw-2023.3.3.dist-info/LICENSE
pybw-2023.3.3.dist-info/METADATA
pybw-2023.3.3.dist-info/WHEEL
pybw-2023.3.3.dist-info/top_level.txt
pybw-2023.3.3.dist-info/RECORD
