Metadata-Version: 2.1
Name: pybw
Version: 2023.3.3
Summary: pybw
Home-page: https://pubowei.cn
Author: Bowei Pu
Author-email: pubowei@foxmail.com
License: MIT
Project-URL: Docs, https://pubowei.cn
Project-URL: Package, https://pypi.org/project/pybw
Project-URL: Repo, https://gitee.com/pubowei/pybw
Keywords: pybw,tools
Classifier: Development Status :: 4 - Beta
Classifier: Intended Audience :: Science/Research
Classifier: License :: OSI Approved :: MIT License
Classifier: Operating System :: OS Independent
Classifier: Programming Language :: Python :: 3.6
Requires-Python: >=3.6
License-File: LICENSE
